metametric/__init__.py
metametric/dsl.py
metametric/core/__init__.py
metametric/core/_ilp.py
metametric/core/_problem.py
metametric/core/constraint.py
metametric/core/decorator.py
metametric/core/graph.py
metametric/core/matching.py
metametric/core/matching_metrics.py
metametric/core/metric.py
metametric/core/metric_suite.py
metametric/core/normalizers.py
metametric/core/path.py
metametric/core/reduction.py
metametric/core/state.py
metametric/metrics/__init__.py
metametric/metrics/coref.py
metametric/metrics/event_extraction.py
metametric/metrics/semantic_parsing.py
metametric/structures/__init__.py
metametric/structures/amr.py
metametric/structures/ie.py
metametric-0.2.1.dist-info/METADATA
metametric-0.2.1.dist-info/WHEEL
metametric-0.2.1.dist-info/RECORD
