Metadata-Version: 2.3
Name: metametric
Version: 0.2.1
Summary: A Unified View of Evaluation Metrics for Structured Prediction
Author-email: Tongfei Chen <tongfei@pm.me>, Yunmo Chen <chanwanmok@gmail.com>, Will Gantt <wgantt.iv@gmail.com>
Requires-Python: >=3.9
Requires-Dist: numpy
Requires-Dist: scipy
